pocketoptionapi/__init__.py
pocketoptionapi/api.py
pocketoptionapi/constants.py
pocketoptionapi/expiration.py
pocketoptionapi/global_value.py
pocketoptionapi/pocket.py
pocketoptionapi/stable_api.py
pocketoptionapi/teste_temp.py
pocketoptionapi/backend/__init__.py
pocketoptionapi/backend/ws/__init__.py
pocketoptionapi/backend/ws/client.py
pocketoptionapi/backend/ws/chat/__init__.py
pocketoptionapi/login/__init__.py
pocketoptionapi/login/test/__init__.py
pocketoptionapi/login/test/login.py
pocketoptionapi/test/__init__.py
pocketoptionapi/test/webdrivertest.py
pocketoptionapi/ws/__init__.py
pocketoptionapi/ws/client.py
pocketoptionapi/ws/chanels/__init__.py
pocketoptionapi/ws/chanels/base.py
pocketoptionapi/ws/chanels/buyv3.py
pocketoptionapi/ws/chanels/candles.py
pocketoptionapi/ws/chanels/get_balances.py
pocketoptionapi/ws/chanels/ssid.py
pocketoptionapi/ws/channels/__init__.py
pocketoptionapi/ws/channels/base.py
pocketoptionapi/ws/channels/buyv3.py
pocketoptionapi/ws/channels/candles.py
pocketoptionapi/ws/channels/change_symbol.py
pocketoptionapi/ws/channels/get_balances.py
pocketoptionapi/ws/channels/ssid.py
pocketoptionapi/ws/objects/__init__.py
pocketoptionapi/ws/objects/base.py
pocketoptionapi/ws/objects/candles.py
pocketoptionapi/ws/objects/time_sync.py
pocketoptionapi/ws/objects/timesync.py
pocketoptionapi2-0.1.1.dist-info/METADATA
pocketoptionapi2-0.1.1.dist-info/WHEEL
pocketoptionapi2-0.1.1.dist-info/top_level.txt
pocketoptionapi2-0.1.1.dist-info/RECORD
