Metadata-Version: 2.4
Name: pocketoptionapi2
Version: 0.1.1
Summary: API for integration with PocketOption
Home-page: https://github.com/Mdbaizidtanvir/pocketoptionapi.git
Author: Mdbaizidtanvir
Classifier: Programming Language :: Python :: 3
Classifier: License :: OSI Approved :: MIT License
Classifier: Operating System :: OS Independent
Requires-Python: >=3.6
Requires-Dist: websocket-client>=1.6.1
Requires-Dist: requests>=2.31.0
Requires-Dist: python-dateutil>=2.8.2
Requires-Dist: tzlocal>=5.1
Requires-Dist: websockets>=12.0
Requires-Dist: pandas>=2.0.3
Requires-Dist: colorama>=0.4.6
Requires-Dist: pillow
Requires-Dist: customtkinter
Requires-Dist: scikit-learn
Requires-Dist: setuptools
